hanzidentifier/__init__.py
hanzidentifier/core.py
hanzidentifier/helpers.py
hanzidentifier-1.3.0.dist-info/METADATA
hanzidentifier-1.3.0.dist-info/WHEEL
hanzidentifier-1.3.0.dist-info/licenses/LICENSE.txt
hanzidentifier-1.3.0.dist-info/RECORD
