Metadata-Version: 2.3
Name: hanzidentifier
Version: 1.3.0
Summary: Python module that identifies Chinese text as Simplified or Traditional.
Project-URL: Changes, https://github.com/tsroten/hanzidentifier/blob/main/CHANGES.rst
Project-URL: Issue Tracker, https://github.com/tsroten/hanzidentifier/issues
Project-URL: Source Code, https://github.com/tsroten/hanzidentifier
Author: Thomas Roten
License: MIT
Keywords: characters,chinese,cjk,hanzi,mandarin,simplified,traditional
Classifier: Development Status :: 5 - Production/Stable
Classifier: Intended Audience :: Developers
Classifier: License :: OSI Approved :: MIT License
Classifier: Operating System :: OS Independent
Classifier: Programming Language :: Python
Classifier: Programming Language :: Python :: 3
Classifier: Programming Language :: Python :: 3.9
Classifier: Programming Language :: Python :: 3.10
Classifier: Programming Language :: Python :: 3.11
Classifier: Programming Language :: Python :: 3.12
Classifier: Programming Language :: Python :: 3.13
Classifier: Topic :: Software Development :: Libraries :: Python Modules
Classifier: Topic :: Text Processing :: Linguistic
Requires-Python: >=3.9
Requires-Dist: zhon~=2.1
